setup.py
django_oidc_auth.egg-info/PKG-INFO
django_oidc_auth.egg-info/SOURCES.txt
django_oidc_auth.egg-info/dependency_links.txt
django_oidc_auth.egg-info/requires.txt
django_oidc_auth.egg-info/top_level.txt
django_oidc_auth.egg-info/zip-safe
oidc_auth/__init__.py
oidc_auth/admin.py
oidc_auth/auth.py
oidc_auth/errors.py
oidc_auth/forms.py
oidc_auth/models.py
oidc_auth/settings.py
oidc_auth/urls.py
oidc_auth/utils.py
oidc_auth/views.py
oidc_auth/migrations/0001_initial.py
oidc_auth/migrations/__init__.py
oidc_auth/south_migrations/0001_initial.py
oidc_auth/south_migrations/__init__.py