Metadata-Version: 1.0
Name: django-oidc-auth
Version: 0.0.11
Summary: OpenID Connect client for Django applications
Home-page: UNKNOWN
Author: Lucas S. Magalhães
Author-email: lucas.sampaio@intelie.com.br
License: UNKNOWN
Platform: UNKNOWN
